o7cli/__init__.py
o7cli/__main__.py
o7cli/asg.py
o7cli/base.py
o7cli/cloudformation.py
o7cli/cloudmap.py
o7cli/cloudtrail.py
o7cli/cloudwatch.py
o7cli/codebuild.py
o7cli/codepipeline.py
o7cli/costexplorer.py
o7cli/costing.py
o7cli/ec2.py
o7cli/ecs.py
o7cli/eventbridge.py
o7cli/guardduty.py
o7cli/iam.py
o7cli/lambdafct.py
o7cli/logs.py
o7cli/logstream.py
o7cli/menu.py
o7cli/organizations.py
o7cli/rds.py
o7cli/reports.py
o7cli/s3.py
o7cli/secret.py
o7cli/securityhub.py
o7cli/sns.py
o7cli/ssm.py
o7cli/ssm_ps.py
o7cli/ssoadmin.py
o7cli/stepfct.py
o7cli/sts.py
o7cli-1.8.0.dist-info/licenses/LICENSE
o7cli-1.8.0.dist-info/METADATA
o7cli-1.8.0.dist-info/WHEEL
o7cli-1.8.0.dist-info/entry_points.txt
o7cli-1.8.0.dist-info/top_level.txt
o7cli-1.8.0.dist-info/RECORD
