Metadata-Version: 2.4
Name: o7cli
Version: 1.8.0
Summary: Useful CLI and scripts for O7 Conseils DevOps practice
Author-email: Philippe Gosselin <phil@o7conseils.com>
License:                                  Apache License
Keywords: python,utility,o7conseils,aws,devops,cli
Classifier: Development Status :: 4 - Beta
Classifier: License :: OSI Approved :: Apache Software License
Classifier: Programming Language :: Python :: 3
Classifier: Programming Language :: Python :: 3.10
Classifier: Programming Language :: Python :: 3.11
Classifier: Programming Language :: Python :: 3.12
Requires-Python: >=3.11
License-File: LICENSE
Requires-Dist: boto3>=1.35
Requires-Dist: certifi>=2024.8.30
Requires-Dist: o7util>=1.0.0
Requires-Dist: pandas>=2.2
Provides-Extra: pdf
Requires-Dist: o7pdf>=1.2.0; extra == "pdf"
Provides-Extra: dev
Requires-Dist: pytest; extra == "dev"
Requires-Dist: pytest-cov; extra == "dev"
Requires-Dist: pytest-mock; extra == "dev"
Requires-Dist: ruff; extra == "dev"
Dynamic: license-file
